precellar/__init__.py
precellar/precellar.cpython-39-x86_64-linux-gnu.so
precellar.libs/libcrypto-bdaed0ea.so.1.1.1k
precellar.libs/libssl-60250281.so.1.1.1k
precellar-0.5.1.dist-info/METADATA
precellar-0.5.1.dist-info/WHEEL
precellar-0.5.1.dist-info/RECORD
precellar-0.5.1.dist-info/licenses/LICENSE
