Metadata-Version: 2.4
Name: precellar
Version: 0.5.1
Classifier: Programming Language :: Rust
Classifier: Programming Language :: Python :: Implementation :: CPython
Classifier: Programming Language :: Python :: Implementation :: PyPy
Requires-Dist: pooch==1.8
License-File: LICENSE
Summary: precellar: Single-cell epigenomics preprocessing toolkit
Author-email: Kai Zhang <zhangkai33@westlake.edu.cn>
Requires-Python: >=3.9, <3.14
Project-URL: Homepage, https://lab.kaizhang.org/precellar/
Project-URL: Documentation, https://lab.kaizhang.org/precellar/
Project-URL: Repository, https://github.com/regulatory-genomics/precellar
Project-URL: Issues, https://github.com/regulatory-genomics/precellar/issues
Project-URL: Changelog, https://lab.kaizhang.org/precellar/version/dev/changelog.html
